Metadata-Version: 2.1
Name: drwnt
Version: 1.1
Summary: Simple library to draw neural networks using pygame.
Home-page: UNKNOWN
Author: Jakub Kubin, Karafak
Author-email: karafak7@gmail.com
License: MIT
Keywords: Neural Network,AI,NN
Platform: UNKNOWN
Classifier: Development Status :: 5 - Production/Stable
Classifier: Intended Audience :: Education
Classifier: Operating System :: Microsoft :: Windows :: Windows 10
Classifier: License :: OSI Approved :: MIT License
Classifier: Programming Language :: Python :: 3
License-File: LICENCE.txt
